django_postgres_vault/__init__.py
django_postgres_vault/base.py
django_postgres_vault-0.1.2.dist-info/LICENSE
django_postgres_vault-0.1.2.dist-info/METADATA
django_postgres_vault-0.1.2.dist-info/WHEEL
django_postgres_vault-0.1.2.dist-info/top_level.txt
django_postgres_vault-0.1.2.dist-info/RECORD
