Metadata-Version: 2.1
Name: django-postgres-vault
Version: 0.1.2
Summary: A simple Django database backend that allows rotating access credentials via HashiCorp Vault
Home-page: https://github.com/jciskey/django_postgres_vault
Author: Joe Ciskey
Author-email: jciskey@inceptivecss.com
License: MIT
Platform: UNKNOWN
Classifier: Development Status :: 2 - Pre-Alpha
Classifier: License :: OSI Approved :: MIT License
Classifier: Programming Language :: Python
Classifier: Programming Language :: Python :: 3
Classifier: Programming Language :: Python :: 3.6
Classifier: Programming Language :: Python :: 3.7
Classifier: Programming Language :: Python :: 3.8
Classifier: Framework :: Django
Classifier: Framework :: Django :: 3.0
Requires-Dist: Django (>=3.0)
Requires-Dist: hvac
